dhpcclient/__init__.py
dhpcclient/amd.py
dhpcclient/gui.py
dhpcclient/hpcclient.py
dhpcclient/nvidia.py
dhpcclient/requestproxy.py
dhpcclient/task.py
dhpcclient/taskhandler.py
dhpcclient/tasklogger.py
dhpcclient/etc/empty.txt
dhpcclient/res/icon.png
dhpcclient/share/config_linux.ini
dhpcclient/share/config_windows.ini
dhpcclient-0.7.5.dist-info/DESCRIPTION.rst
dhpcclient-0.7.5.dist-info/METADATA
dhpcclient-0.7.5.dist-info/RECORD
dhpcclient-0.7.5.dist-info/WHEEL
dhpcclient-0.7.5.dist-info/entry_points.txt
dhpcclient-0.7.5.dist-info/metadata.json
dhpcclient-0.7.5.dist-info/top_level.txt
